design.sv
`timescale 1ns/1ps

module lighting_fsm (
    input clk,
    input reset,
    input [1:0] mode_select,  // 00: IDLE, 01: NORMAL, 10: DIMMING, 11: EMERGENCY
    output reg led,
    output reg [1:0] current_state,
    output reg [3:0] counter,
    output reg [7:0] state_name  // For EPWave display
);

    // Define states
    parameter IDLE = 2'b00;
    parameter NORMAL = 2'b01;
    parameter DIMMING = 2'b10;
    parameter EMERGENCY = 2'b11;

    always @(posedge clk or posedge reset) begin
        if (reset) begin
            current_state <= IDLE;
            counter <= 0;
            led <= 0;
        end else begin
            current_state <= mode_select;

            case (mode_select)
                IDLE: begin
                    led <= 0;
                    counter <= 0;
                end
                NORMAL: begin
                    led <= 1;
                    counter <= counter + 1;
                end
                DIMMING: begin
                    counter <= counter + 1;
                    led <= counter[3];  // slow blink
                end
                EMERGENCY: begin
                    counter <= counter + 1;
                    led <= counter[1];  // fast blink
                end
                default: led <= 0;
            endcase
        end
    end

    // Display-friendly state name for waveform
    always @(*) begin
        case (current_state)
            IDLE:      state_name = "ID";
            NORMAL:    state_name = "NO";
            DIMMING:   state_name = "DM";
            EMERGENCY: state_name = "EM";
            default:   state_name = "XX";
        endcase
    end

endmodule

testbench.sv
`timescale 1ns/1ps

module tb_lighting_fsm;

    reg clk;
    reg reset;
    reg [1:0] mode_select;
    wire led;
    wire [1:0] current_state;
    wire [3:0] counter;
    wire [7:0] state_name;

    // Instantiate the FSM module
    lighting_fsm uut (
        .clk(clk),
        .reset(reset),
        .mode_select(mode_select),
        .led(led),
        .current_state(current_state),
        .counter(counter),
        .state_name(state_name)
    );

    // Generate clock
    initial begin
        clk = 0;
        forever #5 clk = ~clk;  // 10ns clock period
    end

    // Stimulus
    initial begin
        $dumpfile("dump.vcd");
        $dumpvars(0, tb_lighting_fsm);

        reset = 1;
        mode_select = 2'b00;
        #10 reset = 0;

        // NORMAL mode
        #10 mode_select = 2'b01;
        $display("[%0t ns] Entered NORMAL mode", $time/1000);

        // DIMMING mode
        #40 mode_select = 2'b10;
        $display("[%0t ns] Entered DIMMING mode", $time/1000);

        // EMERGENCY mode
        #40 mode_select = 2'b11;
        $display("[%0t ns] Entered EMERGENCY mode", $time/1000);

        // Back to IDLE
        #40 mode_select = 2'b00;
        $display("[%0t ns] Returned to IDLE mode", $time/1000);

        #20 $finish;
    end

endmodule

dump.vcd
$date
	Thu Jul  3 15:37:30 2025
$end
$version
	Icarus Verilog
$end
$timescale
	1ps
$end
$scope module tb_lighting_fsm $end
$var wire 8 ! state_name [7:0] $end
$var wire 1 " led $end
$var wire 2 # current_state [1:0] $end
$var wire 4 $ counter [3:0] $end
$var reg 1 % clk $end
$var reg 2 & mode_select [1:0] $end
$var reg 1 ' reset $end
$scope module uut $end
$var wire 1 % clk $end
$var wire 2 ( mode_select [1:0] $end
$var wire 1 ' reset $end
$var parameter 2 ) DIMMING $end
$var parameter 2 * EMERGENCY $end
$var parameter 2 + IDLE $end
$var parameter 2 , NORMAL $end
$var reg 4 - counter [3:0] $end
$var reg 2 . current_state [1:0] $end
$var reg 1 " led $end
$var reg 8 / state_name [7:0] $end
$upscope $end
$upscope $end
$enddefinitions $end
$comment Show the parameter values. $end
$dumpall
b1 ,
b0 +
b11 *
b10 )
$end
#0
$dumpvars
b1000100 /
b0 .
b0 -
b0 (
1'
b0 &
0%
b0 $
b0 #
0"
b1000100 !
$end
#5000
1%
#10000
0%
0'
#15000
1%
#20000
0%
b1 &
b1 (
#25000
b1001111 !
b1001111 /
b1 $
b1 -
1"
b1 #
b1 .
1%
#30000
0%
#35000
b10 $
b10 -
1%
#40000
0%
#45000
b11 $
b11 -
1%
#50000
0%
#55000
b100 $
b100 -
1%
#60000
0%
b10 &
b10 (
#65000
b1001101 !
b1001101 /
0"
b101 $
b101 -
b10 #
b10 .
1%
#70000
0%
#75000
b110 $
b110 -
1%
#80000
0%
#85000
b111 $
b111 -
1%
#90000
0%
#95000
b1000 $
b1000 -
1%
#100000
0%
b11 &
b11 (
#105000
b1001 $
b1001 -
b11 #
b11 .
1%
#110000
0%
#115000
b1010 $
b1010 -
1%
#120000
0%
#125000
1"
b1011 $
b1011 -
1%
#130000
0%
#135000
b1100 $
b1100 -
1%
#140000
0%
b0 &
b0 (
#145000
b1000100 !
b1000100 /
b0 $
b0 -
0"
b0 #
b0 .
1%
