design.sv
`timescale 1ns/1ps

module led_control (
    input clk,
    input reset,
    output reg [3:0] leds
);

always @(posedge clk or posedge reset) begin
    if (reset)
        leds <= 4'b0000;
    else
        leds <= leds + 1;
end

endmodule

testbench.sv
`timescale 1ns/1ps

module tb_led_control;

reg clk;
reg reset;
wire [3:0] leds;

led_control uut (
    .clk(clk),
    .reset(reset),
    .leds(leds)
);

// Clock generation
initial begin
    clk = 0;
    forever #5 clk = ~clk;
end

// Simulation and waveform
initial begin
    $dumpfile("dump.vcd");
    $dumpvars(0, tb_led_control);

    reset = 1;
    #20;
    reset = 0;
    #100;
    $finish;
end

endmodule

dump.vcd
$date
	Thu Jul  3 14:11:24 2025
$end
$version
	Icarus Verilog
$end
$timescale
	1ps
$end
$scope module tb_led_control $end
$var wire 4 ! leds [3:0] $end
$var reg 1 " clk $end
$var reg 1 # reset $end
$scope module uut $end
$var wire 1 " clk $end
$var wire 1 # reset $end
$var reg 4 $ leds [3:0] $end
$upscope $end
$upscope $end
$enddefinitions $end
$comment Show the parameter values. $end
$dumpall
$end
#0
$dumpvars
b0 $
1#
0"
b0 !
$end
#5000
1"
#10000
0"
#15000
1"
#20000
0"
0#
#25000
b1 !
b1 $
1"
#30000
0"
#35000
b10 !
b10 $
1"
#40000
0"
#45000
b11 !
b11 $
1"
#50000
0"
#55000
b100 !
b100 $
1"
#60000
0"
#65000
b101 !
b101 $
1"
#70000
0"
#75000
b110 !
b110 $
1"
#80000
0"
#85000
b111 !
b111 $
1"
#90000
0"
#95000
b1000 !
b1000 $
1"
#100000
0"
#105000
b1001 !
b1001 $
1"
#110000
0"
#115000
b1010 !
b1010 $
1"
