design.sv
module pwm_generator(
    input clk,
    input [3:0] duty_cycle,
    output reg pwm_out
);
    reg [3:0] counter = 0;

    always @(posedge clk) begin
        counter <= counter + 1;
        pwm_out <= (counter < duty_cycle) ? 1 : 0;
    end
endmodule

module led_mux(
    input [1:0] sel,
    input pwm1, pwm2, pwm3, pwm4,
    output reg led_out
);
    always @(*) begin
        case(sel)
            2'b00: led_out = pwm1;
            2'b01: led_out = pwm2;
            2'b10: led_out = pwm3;
            2'b11: led_out = pwm4;
        endcase
    end
endmodule

testbench.sv
module testbench;
    reg clk;
    reg [3:0] duty1 = 4'd4, duty2 = 4'd8, duty3 = 4'd12, duty4 = 4'd15;
    reg [1:0] sel;
    wire pwm1, pwm2, pwm3, pwm4, led_out;

    always #5 clk = ~clk;

    pwm_generator PWM1(clk, duty1, pwm1);
    pwm_generator PWM2(clk, duty2, pwm2);
    pwm_generator PWM3(clk, duty3, pwm3);
    pwm_generator PWM4(clk, duty4, pwm4);
    led_mux MUX(sel, pwm1, pwm2, pwm3, pwm4, led_out);

    initial begin
        $dumpfile("wave.vcd");
        $dumpvars(0, testbench);
        clk = 0;
        sel = 2'b00;

        #50 sel = 2'b01;
        #50 sel = 2'b10;
        #50 sel = 2'b11;
        #100 $finish;
    end
endmodule

wave.vcd
$date
	Thu Jul  3 14:09:27 2025
$end
$version
	Icarus Verilog
$end
$timescale
	1s
$end
$scope module testbench $end
$var wire 1 ! pwm4 $end
$var wire 1 " pwm3 $end
$var wire 1 # pwm2 $end
$var wire 1 $ pwm1 $end
$var wire 1 % led_out $end
$var reg 1 & clk $end
$var reg 4 ' duty1 [3:0] $end
$var reg 4 ( duty2 [3:0] $end
$var reg 4 ) duty3 [3:0] $end
$var reg 4 * duty4 [3:0] $end
$var reg 2 + sel [1:0] $end
$scope module MUX $end
$var wire 2 , sel [1:0] $end
$var wire 1 ! pwm4 $end
$var wire 1 " pwm3 $end
$var wire 1 # pwm2 $end
$var wire 1 $ pwm1 $end
$var reg 1 % led_out $end
$upscope $end
$scope module PWM1 $end
$var wire 1 & clk $end
$var wire 4 - duty_cycle [3:0] $end
$var reg 4 . counter [3:0] $end
$var reg 1 $ pwm_out $end
$upscope $end
$scope module PWM2 $end
$var wire 1 & clk $end
$var wire 4 / duty_cycle [3:0] $end
$var reg 4 0 counter [3:0] $end
$var reg 1 # pwm_out $end
$upscope $end
$scope module PWM3 $end
$var wire 1 & clk $end
$var wire 4 1 duty_cycle [3:0] $end
$var reg 4 2 counter [3:0] $end
$var reg 1 " pwm_out $end
$upscope $end
$scope module PWM4 $end
$var wire 1 & clk $end
$var wire 4 3 duty_cycle [3:0] $end
$var reg 4 4 counter [3:0] $end
$var reg 1 ! pwm_out $end
$upscope $end
$upscope $end
$enddefinitions $end
$comment Show the parameter values. $end
$dumpall
$end
#0
$dumpvars
b0 4
b1111 3
b0 2
b1100 1
b0 0
b1000 /
b0 .
b100 -
b0 ,
b0 +
b1111 *
b1100 )
b1000 (
b100 '
0&
x%
x$
x#
x"
x!
$end
#5
1%
1$
b1 .
1#
b1 0
1"
b1 2
1!
b1 4
1&
#10
0&
#15
b10 4
b10 2
b10 0
b10 .
1&
#20
0&
#25
b11 .
b11 0
b11 2
b11 4
1&
#30
0&
#35
b100 4
b100 2
b100 0
b100 .
1&
#40
0&
#45
0%
0$
b101 .
b101 0
b101 2
b101 4
1&
#50
1%
0&
b1 +
b1 ,
#55
b110 4
b110 2
b110 0
b110 .
1&
#60
0&
#65
b111 .
b111 0
b111 2
b111 4
1&
#70
0&
#75
b1000 4
b1000 2
b1000 0
b1000 .
1&
#80
0&
#85
0%
b1001 .
0#
b1001 0
b1001 2
b1001 4
1&
#90
0&
#95
b1010 4
b1010 2
b1010 0
b1010 .
1&
#100
1%
0&
b10 +
b10 ,
#105
b1011 .
b1011 0
b1011 2
b1011 4
1&
#110
0&
#115
b1100 4
b1100 2
b1100 0
b1100 .
1&
#120
0&
#125
0%
b1101 .
b1101 0
0"
b1101 2
b1101 4
1&
#130
0&
#135
b1110 4
b1110 2
b1110 0
b1110 .
1&
#140
0&
#145
b1111 .
b1111 0
b1111 2
b1111 4
1&
#150
1%
0&
b11 +
b11 ,
#155
0%
0!
b0 4
b0 2
b0 0
b0 .
1&
#160
0&
#165
1%
1$
b1 .
1#
b1 0
1"
b1 2
1!
b1 4
1&
#170
0&
#175
b10 4
b10 2
b10 0
b10 .
1&
#180
0&
#185
b11 .
b11 0
b11 2
b11 4
1&
#190
0&
#195
b100 4
b100 2
b100 0
b100 .
1&
#200
0&
#205
0$
b101 .
b101 0
b101 2
b101 4
1&
#210
0&
#215
b110 4
b110 2
b110 0
b110 .
1&
#220
0&
#225
b111 .
b111 0
b111 2
b111 4
1&
#230
0&
#235
b1000 4
b1000 2
b1000 0
b1000 .
1&
#240
0&
#245
b1001 .
0#
b1001 0
b1001 2
b1001 4
1&
